skyhub/__init__.py
skyhub/__main__.py
skyhub/controllers/__init__.py
skyhub/controllers/bling_controller.py
skyhub/controllers/skyhub_controller.py
skyhub/controllers/via_varejo_controller.py
skyhub/loggin_config.py
skyhub/models/__init__.py
skyhub/models/produto.py
skyhub/utils/__init__.py
skyhub/utils/csv_parser.py
skyhub/utils/telegram_erros.py
skyhub-1.2.5.dist-info/WHEEL
skyhub-1.2.5.dist-info/METADATA
skyhub-1.2.5.dist-info/RECORD
